.DS_Store
DQbee/AST_walk.py
DQbee/Combinations.py
DQbee/DQuadratization.py
DQbee/EquationSystem.py
DQbee/Simulation.py
DQbee/__init__.py
Package/AST_walk.py
Package/Combinations.py
Package/DQuadratization.py
Package/EquationSystem.py
Package/__init__.py
DQbee-0.1.6.dist-info/LICENSE
DQbee-0.1.6.dist-info/METADATA
DQbee-0.1.6.dist-info/WHEEL
DQbee-0.1.6.dist-info/top_level.txt
DQbee-0.1.6.dist-info/RECORD
