Metadata-Version: 2.1
Name: DQbee
Version: 0.1.6
Summary: DQode is a Python Library to compute the optimal inner-quadratic quadratization and dissipative quadratization of a given polynomial ODE system.
Home-page: https://github.com/yubocai-poly/Dissipative-Quadratiation-Package
Author: Yubo Cai, Gleb Pogudin
Author-email: yubocai0811@gmail.com, pogudin.gleb@gmail.com
Maintainer: Yubo Cai
Maintainer-email: yubocai0811@gmail.com
License: MIT
Project-URL: Code, https://github.com/yubocai-poly/Dissipative-Quadratiation-Package/
Project-URL: Issue tracker, https://github.com/yubocai-poly/Dissipative-Quadratiation-Package/issues
Keywords: quadratization,differential equation,symbolic computing
Classifier: Operating System :: OS Independent
Classifier: Topic :: Text Processing :: Indexing
Classifier: Topic :: Utilities
Classifier: Topic :: Software Development :: Libraries :: Python Modules
Classifier: License :: OSI Approved :: BSD License
Classifier: Programming Language :: Python
Classifier: Programming Language :: Python :: 3.8
Classifier: Programming Language :: Python :: 3.9
Classifier: Programming Language :: Python :: 3.10
Classifier: Programming Language :: Python :: 3.11
Requires-Python: >=3.8
License-File: LICENSE
Requires-Dist: sympy
Requires-Dist: numpy
Requires-Dist: scipy
Requires-Dist: matplotlib
Requires-Dist: tbcontrol
